[
{"id": "1363436622", "set-id": "42108", "description": "Lego Technik Technic 8043, 42009, 42043, 42055, 42100, 42108", "price": " VB", "versand": "Versand m\u00f6glich"},
{"id": "1344469152", "set-id": "42108", "description": "Lego 42108 Kran-LKW Aufkleber Bauanleitung OVP", "price": " VB", "versand": "Versand m\u00f6glich"},
{"id": "1468744078", "set-id": "42108", "description": "Lego Technic Kran 42108", "price": "48 \u20ac VB", "versand": null},
{"id": "1478864162", "set-id": "42108", "description": "LEGO 42108  Kran LKW Technic Bauset", "price": "50 \u20ac", "versand": "Versand m\u00f6glich"},
{"id": "1466039968", "set-id": "42108", "description": "Lego Technic 42108 neuwertig", "price": "55 \u20ac VB", "versand": "Versand m\u00f6glich"},
{"id": "1486036632", "set-id": "42108", "description": "LEGO Technic 42108 Kran-LKW", "price": "60 \u20ac", "versand": "Versand m\u00f6glich"},
{"id": "1484909220", "set-id": "42108", "description": "Lego Technic 42108 Kran LKW", "price": "60 \u20ac", "versand": null},
{"id": "1474621862", "set-id": "42108", "description": "Lego 42108 Kran", "price": "60 \u20ac", "versand": "Versand m\u00f6glich"},
{"id": "1478955741", "set-id": "42108", "description": "lego technic 42108  neu OVP", "price": "60 \u20ac VB", "versand": "Versand m\u00f6glich"},
{"id": "1471796264", "set-id": "42108", "description": "42108 Lego Technic Mobile Crane // neu", "price": "65 \u20ac", "versand": "Versand m\u00f6glich"},
{"id": "1469363041", "set-id": "42108", "description": "Lego Technic 42108", "price": "65 \u20ac VB", "versand": null},
{"id": "1463554334", "set-id": "42108", "description": "LEGO TECHNIC/TECHNIK 42108 MOBILE CRANE mit OVP", "price": "65 \u20ac VB", "versand": "Versand m\u00f6glich"},
{"id": "1445166080", "set-id": "42108", "description": "LEGO TECHNIC/TECHNIK 42108 MOBILE CRANE mit OVP", "price": "65 \u20ac VB", "versand": "Versand m\u00f6glich"},
{"id": "1419951849", "set-id": "42108", "description": "Original Lego Technic Kranwagen, BauNr.42108", "price": "70 \u20ac", "versand": "Versand m\u00f6glich"},
{"id": "1479816766", "set-id": "42108", "description": "Lego Technic- 42108 Mobile Crane Neu&OVP", "price": "70 \u20ac VB", "versand": "Versand m\u00f6glich"},
{"id": "1424467662", "set-id": "42108", "description": "Lego Technic 42108", "price": "70 \u20ac VB", "versand": "Versand m\u00f6glich"},
{"id": "1470278574", "set-id": "42108", "description": "LEGO\u00ae Technic 42108 Kran-LKW- mobiler Kranwagen Lasten NEU & OVP", "price": "73 \u20ac", "versand": null},
{"id": "1474310705", "set-id": "42108", "description": "LEGO TECHNIC 42108 KRAN-LKW", "price": "75 \u20ac", "versand": null},
{"id": "1453070561", "set-id": "42108", "description": "\u2b50 Lego 42108 mobiler Kranwagen | NEU | OVP", "price": "75 \u20ac", "versand": "Versand m\u00f6glich"},
{"id": "1424348279", "set-id": "42108", "description": "Lego Technik 42108 Mobiler Kran", "price": "75 \u20ac", "versand": "Versand m\u00f6glich"},
{"id": "1486306729", "set-id": "42108", "description": "Lego Technic Lkw Kran 42108", "price": "75 \u20ac VB", "versand": "Versand m\u00f6glich"},
{"id": "1476603472", "set-id": "42108", "description": "Lego Technik 42108 Kran LKW NEU OVP", "price": "75 \u20ac VB", "versand": "Versand m\u00f6glich"},
{"id": "1484664714", "set-id": "42108", "description": "Lego technic 42108 Kran Neu/Ovp", "price": "78 \u20ac", "versand": "Versand m\u00f6glich"},
{"id": "1406787464", "set-id": "42108", "description": "LEGO Technic Technik 42108", "price": "80 \u20ac", "versand": "Versand m\u00f6glich"},
{"id": "1447706423", "set-id": "42108", "description": "Lego Technic 42108 versiegelt", "price": "90 \u20ac VB", "versand": "Versand m\u00f6glich"},
{"id": "1476010043", "set-id": "42107", "description": "Lego Technic 42107 OVP", "price": " VB", "versand": "Versand m\u00f6glich"},
{"id": "1434403015", "set-id": "42107", "description": "Lego Ducati 42107, BMW 42063, 10269 Harley", "price": " VB", "versand": "Versand m\u00f6glich"},
{"id": "1486170357", "set-id": "42107", "description": "LEGO technic Ducati Panigale V4 R, 42107", "price": "40 \u20ac", "versand": "Versand m\u00f6glich"},
{"id": "1488281689", "set-id": "42107", "description": "Lego 42107 Ducati Panigale V4R mit OVP unbespielt", "price": "45 \u20ac VB", "versand": "Versand m\u00f6glich"},
{"id": "1475484170", "set-id": "42107", "description": "Lego Technic Motorrad 42107 neu!", "price": "49 \u20ac", "versand": "Versand m\u00f6glich"},
{"id": "1455905229", "set-id": "42107", "description": "LEGO\u00ae Technic 42107 Ducati Panigale V4 R - NEU - Modell Bausatz", "price": "49 \u20ac", "versand": "Versand m\u00f6glich"},
{"id": "1472775910", "set-id": "42107", "description": "LEGO DUCATI 42107", "price": "50 \u20ac", "versand": "Versand m\u00f6glich"},
{"id": "1417797045", "set-id": "42107", "description": "42107 Lego Technic Ducati Panigale V4 R NEU OVP", "price": "50 \u20ac", "versand": "Versand m\u00f6glich"},
{"id": "1473529969", "set-id": "42107", "description": "Lego Technic Motorrad 42107 neu!", "price": "53 \u20ac VB", "versand": "Versand m\u00f6glich"},
{"id": "1487963022", "set-id": "42107", "description": "LEGO\u00ae Technic 42107 Ducati Panigale V4 R BRANDNEU von H\u00e4ndler !!", "price": "54 \u20ac", "versand": "Versand m\u00f6glich"},
{"id": "1446792358", "set-id": "42107", "description": "Lego Technic 42107 Ducati Panigale V4R NEU&OVP", "price": "55 \u20ac", "versand": null},
{"id": "1426181441", "set-id": "42107", "description": "LEGO 42107 Technic Ducati Panigale V4 R - Neu, OVP", "price": "55 \u20ac", "versand": "Versand m\u00f6glich"},
{"id": "1474105296", "set-id": "42107", "description": "Lego ducati 42107", "price": "55 \u20ac VB", "versand": "Versand m\u00f6glich"},
{"id": "1488444245", "set-id": "42100", "description": "Lego Technic 42100 Liebherr Bagger R9800", "price": " VB", "versand": "Versand m\u00f6glich"},
{"id": "1479796695", "set-id": "42100", "description": "Lego Technik 42100 Liebherr Bagger 42055 Schaufelradbagger usw.", "price": " VB", "versand": null},
{"id": "1476009869", "set-id": "42100", "description": "Lego Technic 42100 OVP", "price": " VB", "versand": "Versand m\u00f6glich"},
{"id": "1469085746", "set-id": "42100", "description": "Lego Technic 42100 Liebherr Bagger Neu", "price": " VB", "versand": "Versand m\u00f6glich"},
{"id": "1404528127", "set-id": "42100", "description": "Lego technik Sammlung, 42009,42055,42050,42100....", "price": " VB", "versand": "Versand m\u00f6glich"},
{"id": "1389408638", "set-id": "42100", "description": "Lego 42100 Liebherr Bagger Leerkarton / OVP", "price": " VB", "versand": "Versand m\u00f6glich"},
{"id": "1380143653", "set-id": "42100", "description": "Lego Technik Technic 8043, 42030, 8265, 9397, 42100, 42009, 9398", "price": " VB", "versand": "Versand m\u00f6glich"},
{"id": "1363436622", "set-id": "42100", "description": "Lego Technik Technic 8043, 42009, 42043, 42055, 42100, 42108", "price": " VB", "versand": "Versand m\u00f6glich"},
{"id": "1414602149", "set-id": "42100", "description": "LEGO Technic 42100 Liebherr R 9800 Sticker / Aufkleber - NEU -", "price": "20 \u20ac", "versand": "Versand m\u00f6glich"},
{"id": "1414595647", "set-id": "42100", "description": "LEGO Technic 42100 Liebherr R 9800 Sticker / Aufkleber - NEU -", "price": "24 \u20ac", "versand": "Versand m\u00f6glich"},
{"id": "1437963374", "set-id": "42100", "description": "LED Beleuchtungsset f\u00fcr Lego 42100 Liebherr Bagger", "price": "35 \u20ac", "versand": "Versand m\u00f6glich"},
{"id": "1481456529", "set-id": "42100", "description": "Lego Technik Liebherr Bagger 42100", "price": "220 \u20ac VB", "versand": "Versand m\u00f6glich"},
{"id": "1474397643", "set-id": "42100", "description": "Lego Technic 42100 Liebherr Bagger. Noch nie bespielt. Wie neu", "price": "239 \u20ac", "versand": null},
{"id": "1486198108", "set-id": "42100", "description": "Lego Technic 42100 LIebherr R9800", "price": "240 \u20ac", "versand": "Versand m\u00f6glich"},
{"id": "1487728032", "set-id": "42100", "description": "Lego Technic 42100", "price": "240 \u20ac VB", "versand": null},
{"id": "1475766767", "set-id": "42100", "description": "LEGO Technic 42043 - Mercedes-Benz Arocs Tausch 42100", "price": "249 \u20ac", "versand": "Versand m\u00f6glich"},
{"id": "1477557132", "set-id": "42109", "description": "Lego Technic 42109 Top-Gear Ralleyauto mit App-Steuerung NEU / OV", "price": " VB", "versand": "Versand m\u00f6glich"},
{"id": "1485872823", "set-id": "42100", "description": "LEGO 42100 Technic Liebherr Bagger R 9800", "price": "250 \u20ac", "versand": null},
{"id": "1488232014", "set-id": "42100", "description": "Lego Technic Liebherr Bagger 42100", "price": "250 \u20ac VB", "versand": "Versand m\u00f6glich"},
{"id": "1460427520", "set-id": "42109", "description": "Lego Technic 42109 Ralleyauto Bauanleitung", "price": "12 \u20ac VB", "versand": "Versand m\u00f6glich"},
{"id": "1488720932", "set-id": "42109", "description": "Lego 42109 Top Gear Rally Car", "price": "60 \u20ac", "versand": "Versand m\u00f6glich"},
{"id": "1479818948", "set-id": "42109", "description": "Lego Technic- 42109 Rally Car Neu&OVP", "price": "70 \u20ac VB", "versand": "Versand m\u00f6glich"},
{"id": "1477273083", "set-id": "42100", "description": "Lego Technic 42100 Liebherr Bagger", "price": "250 \u20ac VB", "versand": "Versand m\u00f6glich"},
{"id": "1455469853", "set-id": "42100", "description": "Lego 42100 Technik  Versand incl.", "price": "255 \u20ac", "versand": "Versand m\u00f6glich"},
{"id": "1485498247", "set-id": "42109", "description": "LEGO Technic - Top-Gear Ralleyauto mit App-Steuerung (42109) Neu", "price": "75 \u20ac", "versand": "Versand m\u00f6glich"},
{"id": "1478930174", "set-id": "42078", "description": "2x Lego Mack Anthem 42078 NEU + versiegelt im Umkarton", "price": "299 \u20ac", "versand": "Versand m\u00f6glich"},
{"id": "1489175615", "set-id": "42100", "description": "Lego Set 42100 mit OVP Liebherr Bagger 9800 inkl. LED Set", "price": "255 \u20ac VB", "versand": "Versand m\u00f6glich"},
{"id": "1486086630", "set-id": "42109", "description": "Lego 42109 Top Gear Rally Car OVP neu", "price": "75 \u20ac VB", "versand": "Versand m\u00f6glich"},
{"id": "1475786415", "set-id": "42109", "description": "Lego Technic 42109 Top Gear Rally Car App Control gebraucht", "price": "75 \u20ac VB", "versand": "Versand m\u00f6glich"},
{"id": "1487090480", "set-id": "42078", "description": "Lego 42078", "price": " VB", "versand": "Versand m\u00f6glich"},
{"id": "1487088044", "set-id": "42078", "description": "Lego 42078", "price": " VB", "versand": "Versand m\u00f6glich"},
{"id": "1484088211", "set-id": "42100", "description": "Lego Technic 42100", "price": "260 \u20ac VB", "versand": "Versand m\u00f6glich"},
{"id": "1482637273", "set-id": "42029", "description": "Lego Technik 42029", "price": " VB", "versand": "Versand m\u00f6glich"},
{"id": "1472237651", "set-id": "42109", "description": "Lego Technic 42109 Rally Auto", "price": "75 \u20ac VB", "versand": "Versand m\u00f6glich"},
{"id": "1487142998", "set-id": "42109", "description": "NEU Lego Technik 42109 Ralley mit Appsteuerung", "price": "80 \u20ac", "versand": "Versand m\u00f6glich"},
{"id": "1477975543", "set-id": "42109", "description": "LEGO Technic - Top-Gear Ralleyauto mit App-Steuerung (42109)", "price": "80 \u20ac", "versand": "Versand m\u00f6glich"},
{"id": "1476013979", "set-id": "42078", "description": "Lego Technic 42078 OVP", "price": " VB", "versand": "Versand m\u00f6glich"},
{"id": "1466075069", "set-id": "42100", "description": "Lego 42100 Liebherr 9800", "price": "265 \u20ac VB", "versand": "Versand m\u00f6glich"},
{"id": "1482535289", "set-id": "42029", "description": "Lego Technic 42029 Pick Up Truck", "price": " VB", "versand": null},
{"id": "1457659353", "set-id": "42109", "description": "Lego 42109", "price": "80 \u20ac VB", "versand": "Versand m\u00f6glich"},
{"id": "1463778636", "set-id": "42109", "description": "LEGO Technic - 42109 - Top-Gear Ralleyauto mit App-Steuerung", "price": "87 \u20ac", "versand": "Versand m\u00f6glich"},
{"id": "1456624792", "set-id": "42109", "description": "Lego Technik App-controlled Top Gear Rally Car 42109", "price": "90 \u20ac VB", "versand": "Versand m\u00f6glich"},
{"id": "1462390312", "set-id": "42078", "description": "Lego Mack Technic 42078", "price": " VB", "versand": "Versand m\u00f6glich"},
{"id": "1456694606", "set-id": "42078", "description": "Lego Mack Anthem 42078", "price": " VB", "versand": "Versand m\u00f6glich"},
{"id": "1451674833", "set-id": "42078", "description": "Suche Lego Technic 42078 Mack komplett", "price": " VB", "versand": "Gesuch"},
{"id": "1480974650", "set-id": "42100", "description": "Lego Technic Bagger Liebherr 42100", "price": "270 \u20ac VB", "versand": "Versand m\u00f6glich"},
{"id": "1375973137", "set-id": "42100", "description": "LEGO Technic - 42100 Liebherr Bagger R 9800", "price": "274 \u20ac", "versand": "Versand m\u00f6glich"},
{"id": "1464498302", "set-id": "42029", "description": "Lego Technic Kartons 42009 42070 42038 42039 42029", "price": " VB", "versand": "Versand m\u00f6glich"},
{"id": "1191706668", "set-id": "42029", "description": "Lego Technic 42029 Truck Pick up", "price": " VB", "versand": null},
{"id": "1298537799", "set-id": "42109", "description": "Lego Technic 42109 Top Gear", "price": "99 \u20ac", "versand": "Versand m\u00f6glich"},
{"id": "1472922955", "set-id": "42109", "description": "LEGO Technic 42109 Top-Gear Ralleyauto mit App-Steuerung NEU&OVP", "price": "120 \u20ac VB", "versand": "Versand m\u00f6glich"},
{"id": "1488909461", "set-id": "42055", "description": "42055 Lego Technic Schaufelradbagger", "price": " VB", "versand": null},
{"id": "1467970007", "set-id": "42094", "description": "Lego Technic 42094", "price": "20 \u20ac VB", "versand": null},
{"id": "1428516996", "set-id": "42078", "description": "Lego technic 42078 MACK Truck Anleitung + Sticker Aufkleber", "price": " VB", "versand": "Versand m\u00f6glich"},
{"id": "1486545508", "set-id": "42078", "description": "Lego Technic 42078 Mack Anleitung", "price": "5 \u20ac", "versand": "Versand m\u00f6glich"},
{"id": "1195040712", "set-id": "42078", "description": "Lego technic 42078 Mack truck Sticker Aufkleber lego technik", "price": "7 \u20ac", "versand": "Versand m\u00f6glich"},
{"id": "1415015352", "set-id": "42110", "description": "LEGO Technic 42110 - Land Rover Defender | NEU & Unge\u00f6ffnet", "price": "120 \u20ac", "versand": "Versand m\u00f6glich"},
{"id": "1488624293", "set-id": "42029", "description": "Lego Technic 42029 Pick up Truck", "price": "60 \u20ac", "versand": "Versand m\u00f6glich"},
{"id": "1469151130", "set-id": "42029", "description": "Lego Technic Pick-Up Truck -42029-", "price": "60 \u20ac", "versand": null},
{"id": "1476257142", "set-id": "42112", "description": "Lego Technic 42112 OVP", "price": " VB", "versand": "Versand m\u00f6glich"},
{"id": "1476010217", "set-id": "42111", "description": "Lego Technic 42111 OVP", "price": " VB", "versand": "Versand m\u00f6glich"},
{"id": "1489287250", "set-id": "42109", "description": "Lego Technik Top Gear 42109", "price": "175 \u20ac VB", "versand": "Versand m\u00f6glich"},
{"id": "1488608232", "set-id": "42055", "description": "LEGO Technic Schaufelradbagger 42055", "price": " VB", "versand": "Versand m\u00f6glich"},
{"id": "1486068764", "set-id": "42055", "description": "LEGO Technik 42055", "price": " VB", "versand": "Versand m\u00f6glich"},
{"id": "1486066935", "set-id": "42055", "description": "Lego 42055 technic", "price": " VB", "versand": "Versand m\u00f6glich"},
{"id": "1475718345", "set-id": "42094", "description": "Lego Technic Raupenlader 42094", "price": "30 \u20ac", "versand": "Versand m\u00f6glich"},
{"id": "1430851075", "set-id": "42094", "description": "Lego Technic Raupenlader 42094", "price": "30 \u20ac", "versand": "Versand m\u00f6glich"},
{"id": "1092868829", "set-id": "42078", "description": "Lego technic 42078 Mack Truck Bauanleitung neu BA Technik", "price": "7 \u20ac", "versand": "Versand m\u00f6glich"},
{"id": "1483042836", "set-id": "42110", "description": "Lego Technic 42110 Land Rover Defender", "price": " VB", "versand": null},
{"id": "1476011450", "set-id": "42110", "description": "Lego Technic 42110 OVP", "price": " VB", "versand": "Versand m\u00f6glich"},
{"id": "1486263294", "set-id": "42029", "description": "Pick up Truck Lego Technic 42029", "price": "65 \u20ac", "versand": "Versand m\u00f6glich"},
{"id": "1473331699", "set-id": "42029", "description": "LEGO TECHNIC Pick-Up Truck Artikelnummer 42029", "price": "65 \u20ac VB", "versand": "Versand m\u00f6glich"},
{"id": "1467667230", "set-id": "42029", "description": "\u00b0 Lego Technic \u00b0 42029 - Pick-Up Truck", "price": "70 \u20ac", "versand": "Versand m\u00f6glich"},
{"id": "1444344013", "set-id": "42029", "description": "\u00b0 Lego Technic \u00b0 42029 - Pick-Up Truck", "price": "70 \u20ac", "versand": "Versand m\u00f6glich"},
{"id": "1489159608", "set-id": "42112", "description": "LEGO\u00ae Technic 42112 Betonmischer - LKW Modell Neu", "price": "79 \u20ac", "versand": "Versand m\u00f6glich"},
{"id": "1484076126", "set-id": "42112", "description": "LEGO\u00ae Technic 42112 Betonmischer-LKW", "price": "99 \u20ac", "versand": "Versand m\u00f6glich"},
{"id": "1488762986", "set-id": "42112", "description": "Lego Technik Betonmischer 42112", "price": "100 \u20ac", "versand": "Versand m\u00f6glich"},
{"id": "1468036228", "set-id": "42111", "description": "Lego Technic 42111 Karton Technik ohne Inhalt", "price": "5 \u20ac", "versand": "Versand m\u00f6glich"},
{"id": "1487314057", "set-id": "42109", "description": "Lego Technic 42099 und 42109 Control App neu und gebraucht", "price": "245 \u20ac", "versand": "Versand m\u00f6glich"},
{"id": "1485738087", "set-id": "42055", "description": "Lego Technic 42055 Schaufelradbagger", "price": " VB", "versand": "Versand m\u00f6glich"},
{"id": "1481531450", "set-id": "42055", "description": "Lego Mocs 42055 Ultimate, CB Rock Crawler", "price": " VB", "versand": "Versand m\u00f6glich"},
{"id": "1479796695", "set-id": "42055", "description": "Lego Technik 42100 Liebherr Bagger 42055 Schaufelradbagger usw.", "price": " VB", "versand": null},
{"id": "1465341144", "set-id": "42094", "description": "Lego 42094 Technic Raupenlader, bunt", "price": "35 \u20ac", "versand": null},
{"id": "1414063646", "set-id": "42094", "description": "LEGO 42094 Raupenlader", "price": "35 \u20ac", "versand": "Versand m\u00f6glich"},
{"id": "1488025409", "set-id": "42094", "description": "LEGO 42094 Technic Raupenlader", "price": "38 \u20ac VB", "versand": "Versand m\u00f6glich"},
{"id": "1125030141", "set-id": "42078", "description": "Lego technic 42078 Mack Karton OVP  NEU Technik", "price": "8 \u20ac", "versand": null},
{"id": "1375199449", "set-id": "42078", "description": "Lego Technic Aufkleber 42078", "price": "10 \u20ac", "versand": "Versand m\u00f6glich"},
{"id": "1468546669", "set-id": "42110", "description": "Lego 42110", "price": " VB", "versand": "Versand m\u00f6glich"},
{"id": "1269088089", "set-id": "42110", "description": "Lego 42110 Land Rover Defender Bauanleitung + Aufkleberbogen Neu", "price": " VB", "versand": "Versand m\u00f6glich"},
{"id": "1450200424", "set-id": "42110", "description": "Radkappen f\u00fcr den Landrover Defender (42110) von Lego.", "price": "6 \u20ac", "versand": "Versand m\u00f6glich"},
{"id": "1287665203", "set-id": "42029", "description": "Lego Technik 42029", "price": "70 \u20ac", "versand": "Versand m\u00f6glich"},
{"id": "1327664620", "set-id": "42029", "description": "Lego Technik Pick Up Truck (Art. 42029)", "price": "70 \u20ac", "versand": "Versand m\u00f6glich"},
{"id": "1483261436", "set-id": "42029", "description": "Lego Technic 42029 Pick-Up Truck  OVP + BA", "price": "70 \u20ac VB", "versand": "Versand m\u00f6glich"},
{"id": "1411808765", "set-id": "42111", "description": "Lego Technic 42111 Dodge Charger Fast and Furious LEERKARTON", "price": "5 \u20ac VB", "versand": "Versand m\u00f6glich"},
{"id": "1469630638", "set-id": "42111", "description": "Lego Technic 42111 Anleitung Technik unbenutzt", "price": "7 \u20ac", "versand": "Versand m\u00f6glich"},
{"id": "1488177814", "set-id": "42111", "description": "Lego Technic 42111 Dom\u2018s Dodge Charger", "price": "60 \u20ac VB", "versand": null},
{"id": "1486542126", "set-id": "42111", "description": "Lego Dom\u2018s Dodge Charger 42111, Sticker unbenutzt", "price": "64 \u20ac", "versand": "Versand m\u00f6glich"},
{"id": "1476010356", "set-id": "42055", "description": "Lego Technic 42055 OVP", "price": " VB", "versand": "Versand m\u00f6glich"},
{"id": "1473813960", "set-id": "42055", "description": "Lego Technik 42055", "price": " VB", "versand": "Versand m\u00f6glich"},
{"id": "1472436928", "set-id": "42055", "description": "Lego Technik Schaufelradbagger 42055", "price": " VB", "versand": "Versand m\u00f6glich"},
{"id": "1452347838", "set-id": "42094", "description": "Lego Technik, 42094", "price": "39 \u20ac", "versand": "Versand m\u00f6glich"},
{"id": "1044614435", "set-id": "42078", "description": "Biete Lego Technik Mac Anthem Handbuch 42078", "price": "10 \u20ac", "versand": null},
{"id": "1478794866", "set-id": "42078", "description": "42078 Lego Karton + Bauanleitung", "price": "10 \u20ac VB", "versand": null},
{"id": "1360052752", "set-id": "42110", "description": "LEGO - Zubeh\u00f6r f\u00fcr Modell Landrover Defender (42110), Radkappen.", "price": "6 \u20ac", "versand": "Versand m\u00f6glich"},
{"id": "1451744098", "set-id": "42110", "description": "Lego Technik Technic 42110 Leerkarton Karton OVP Neu", "price": "6 \u20ac VB", "versand": "Versand m\u00f6glich"},
{"id": "1474747178", "set-id": "42029", "description": "Lego Pickup Truck 42029", "price": "75 \u20ac", "versand": "Versand m\u00f6glich"},
{"id": "1393540412", "set-id": "42029", "description": "Lego Technic 42029 Pickup Truck 2in1 SUV", "price": "75 \u20ac", "versand": "Versand m\u00f6glich"},
{"id": "1377715526", "set-id": "42029", "description": "! Lego 42029 Pickup rot !", "price": "75 \u20ac", "versand": "Versand m\u00f6glich"},
{"id": "1488852596", "set-id": "42111", "description": "Lego Technic 42111 Dom\u2018s Dodge Charger", "price": "65 \u20ac", "versand": "Versand m\u00f6glich"},
{"id": "1471215532", "set-id": "42055", "description": "Lego Technic Schaufelradbagger (42055)", "price": " VB", "versand": "Versand m\u00f6glich"},
{"id": "1467620270", "set-id": "42055", "description": "LEGO Technic 42055 - Schaufelradbagger ohne OVP", "price": " VB", "versand": null},
{"id": "1465607079", "set-id": "42055", "description": "Lego Technik 42009 verkauft! 42055", "price": " VB", "versand": "Versand m\u00f6glich"},
{"id": "1481885977", "set-id": "42115", "description": "Suche Lego Lamborghini Si\u00e1n 42115", "price": " VB", "versand": "Gesuch"},
{"id": "1451521712", "set-id": "42094", "description": "Lego 42094 Technic Raupenlader", "price": "39 \u20ac", "versand": "Versand m\u00f6glich"},
{"id": "1456475333", "set-id": "42094", "description": "Lego 42094 Technic Raupenlader", "price": "40 \u20ac", "versand": "Versand m\u00f6glich"},
{"id": "1400668845", "set-id": "42094", "description": "Lego Technic 42094 Raupenlader, neuwertig", "price": "40 \u20ac", "versand": "Versand m\u00f6glich"},
{"id": "1410445143", "set-id": "42078", "description": "Bauanleitung Lego Technic 42078", "price": "11 \u20ac VB", "versand": "Versand m\u00f6glich"},
{"id": "1256751745", "set-id": "42078", "description": "Lego Technic 42078 Mack Anthem Leerkarton + Bauanleitung", "price": "25 \u20ac", "versand": "Versand m\u00f6glich"},
{"id": "1484259502", "set-id": "42078", "description": "LEGO 42078 Mack -LKW", "price": "80 \u20ac", "versand": null},
{"id": "1385237187", "set-id": "42110", "description": "Lego Technik Technic 42110 Land Rover Leerkarton Karton OVP Neu", "price": "6 \u20ac VB", "versand": "Versand m\u00f6glich"},
{"id": "1484284448", "set-id": "42110", "description": "Lego Technic - Land Rover Defender (42110) Bedienungsanleitung", "price": "7 \u20ac", "versand": "Versand m\u00f6glich"},
{"id": "992933974", "set-id": "42029", "description": "LEGO Technic 42029 - Pick-Up Truck, OVP komplett Neu 169,90\u20ac", "price": "75 \u20ac", "versand": null},
{"id": "1480688844", "set-id": "42111", "description": "LEGO\u00ae Technic 42111 Technic Dom's Dodge Charger, Bauset", "price": "65 \u20ac", "versand": "Versand m\u00f6glich"},
{"id": "1461819488", "set-id": "42055", "description": "Lego Technik 42055 Schaufelradbagger", "price": " VB", "versand": "Versand m\u00f6glich"},
{"id": "1476009700", "set-id": "42115", "description": "Lego Technic 42115 OVP", "price": " VB", "versand": "Versand m\u00f6glich"},
{"id": "1487742502", "set-id": "42115", "description": "DIY  LED Licht Beleuchtung Kit F\u00fcr LEGO 42115 F\u00fcr Lamborghini Sia", "price": "26 \u20ac", "versand": null},
{"id": "1473203098", "set-id": "42115", "description": "LEGO 42115 Lamborghini Sian KARTON", "price": "34 \u20ac VB", "versand": "Versand m\u00f6glich"},
{"id": "1468915456", "set-id": "42094", "description": "Lego Technik Raupenlader 42094", "price": "40 \u20ac VB", "versand": "Versand m\u00f6glich"},
{"id": "1487917440", "set-id": "42094", "description": "LEGO TECHNIC RAUPENLADER 42094", "price": "42 \u20ac VB", "versand": "Versand m\u00f6glich"},
{"id": "1468769221", "set-id": "42078", "description": "LEGO Technic 42078 - Mack Anthem", "price": "85 \u20ac VB", "versand": "Versand m\u00f6glich"},
{"id": "1483131200", "set-id": "42078", "description": "Lego Technik Mack Anthem Truck 42078", "price": "90 \u20ac", "versand": "Versand m\u00f6glich"},
{"id": "1484524656", "set-id": "42110", "description": "Lego Defender Verpackung 42110", "price": "10 \u20ac", "versand": "Versand m\u00f6glich"},
{"id": "1484274593", "set-id": "42110", "description": "Lego Technic - Land Rover Defender (42110) leer Karton, OVP", "price": "10 \u20ac VB", "versand": "Versand m\u00f6glich"},
{"id": "1361739002", "set-id": "42029", "description": "Lego 42029 Technic Offroader  inkl. Anleitungen und OVP", "price": "75 \u20ac VB", "versand": "Versand m\u00f6glich"},
{"id": "1468833087", "set-id": "42111", "description": "Lego Technic 42111 Dodge Charger", "price": "68 \u20ac", "versand": "Versand m\u00f6glich"},
{"id": "1404528127", "set-id": "42055", "description": "Lego technik Sammlung, 42009,42055,42050,42100....", "price": " VB", "versand": "Versand m\u00f6glich"},
{"id": "1488093123", "set-id": "42115", "description": "LEGO Technic 42115 Lamborghini Si\u00e1n FKP 37", "price": "275 \u20ac", "versand": "Versand m\u00f6glich"},
{"id": "1487132366", "set-id": "42094", "description": "Lego 42094 Tracked Loader", "price": "45 \u20ac", "versand": "Versand m\u00f6glich"},
{"id": "1449044979", "set-id": "42078", "description": "Lego technic Technik 42078 Mack Anthem Truck", "price": "90 \u20ac VB", "versand": "Versand m\u00f6glich"},
{"id": "1449803096", "set-id": "42110", "description": "Karton Lego Technik 42110", "price": "15 \u20ac VB", "versand": "Versand m\u00f6glich"},
{"id": "1476256859", "set-id": "42114", "description": "Lego Technic 42114 OVP", "price": " VB", "versand": "Versand m\u00f6glich"},
{"id": "1313711646", "set-id": "42029", "description": "LEGO Technic 42029 Pick Up Truck 2in1 Neuwertig OVP BA komplett", "price": "79 \u20ac", "versand": "Versand m\u00f6glich"},
{"id": "1466811333", "set-id": "42111", "description": "LEGO\u00ae Technic 42111 Dom's Dodge Charger NEU - Fast&Furious", "price": "69 \u20ac", "versand": "Versand m\u00f6glich"},
{"id": "1389389231", "set-id": "42055", "description": "LEGO Technic 42055 - Schaufelradbagger (NEU + OVP)", "price": " VB", "versand": "Versand m\u00f6glich"},
{"id": "1488511508", "set-id": "42115", "description": "*reserviert* Lego 42115 Lamborghini Sian Neu und OVP", "price": "280 \u20ac", "versand": "Versand m\u00f6glich"},
{"id": "1488379052", "set-id": "42115", "description": "LEGO Technic 42115 Lamborghini Si\u00e1n FKP 37 - neu", "price": "280 \u20ac", "versand": "Versand m\u00f6glich"},
{"id": "1484455778", "set-id": "42094", "description": "Lego technic/technik 42094", "price": "45 \u20ac", "versand": "Versand m\u00f6glich"},
{"id": "1458887403", "set-id": "42094", "description": "Lego Raupenlader 42094", "price": "45 \u20ac", "versand": "Versand m\u00f6glich"},
{"id": "1488235578", "set-id": "42078", "description": "Lego technic 42078 Container Truck", "price": "95 \u20ac VB", "versand": null},
{"id": "1441272555", "set-id": "42078", "description": "LEGO Technic 42078 - Mack Anthem + OVP", "price": "97 \u20ac", "versand": "Versand m\u00f6glich"},
{"id": "1400769687", "set-id": "42110", "description": "LED Beleuchtungs Set f\u00fcr Lego 42110 Range Rover", "price": "35 \u20ac", "versand": "Versand m\u00f6glich"},
{"id": "1483877545", "set-id": "42110", "description": "Lego Technic Landrover Defender 42110 (reserviert)", "price": "70 \u20ac", "versand": null},
{"id": "1477762770", "set-id": "42114", "description": "Lego Technic Technik Einzelteile Sammlung aus 8110 8421 42114", "price": "1 \u20ac VB", "versand": "Versand m\u00f6glich"},
{"id": "1481892477", "set-id": "42114", "description": "Lego Technic Technik Differential  6285646 6285647  aus 42114", "price": "7 \u20ac", "versand": "Versand m\u00f6glich"},
{"id": "1488813698", "set-id": "42029", "description": "Lego Technic Pick-up Truck 42029", "price": "80 \u20ac", "versand": "Versand m\u00f6glich"},
{"id": "1484934257", "set-id": "42111", "description": "Lego Technic 42111 Dom's Dodge Charger inkl.Versand", "price": "70 \u20ac", "versand": "Versand m\u00f6glich"},
{"id": "1474660932", "set-id": "42111", "description": "LEGO Technic / Technik 42111 Dom's Dodge Charger NEU & OVP", "price": "70 \u20ac", "versand": "Versand m\u00f6glich"},
{"id": "1363436622", "set-id": "42055", "description": "Lego Technik Technic 8043, 42009, 42043, 42055, 42100, 42108", "price": " VB", "versand": "Versand m\u00f6glich"},
{"id": "1487956994", "set-id": "42115", "description": "Lego Technic   42115 Lamborghini Si\u00e1n FKP 37\u2606 NEU \u2606", "price": "290 \u20ac", "versand": "Versand m\u00f6glich"},
{"id": "1441220458", "set-id": "42094", "description": "Lego Technic 42094", "price": "45 \u20ac VB", "versand": null},
{"id": "1374179647", "set-id": "42094", "description": "Lego 42094 Technic Raupenlader", "price": "45 \u20ac VB", "versand": "Versand m\u00f6glich"},
{"id": "1471863450", "set-id": "42078", "description": "Lego Technic Truck 42078", "price": "99 \u20ac VB", "versand": "Versand m\u00f6glich"},
{"id": "1440791274", "set-id": "42078", "description": "[Suche] LEGO 42078 Mack Anthem neu oder gebraucht", "price": "99 \u20ac VB", "versand": "Gesuch"},
{"id": "1486345458", "set-id": "42110", "description": "Lego 42110 Land Rover Defender", "price": "85 \u20ac", "versand": null},
{"id": "1487424257", "set-id": "42110", "description": "LEGO 42110 Technic Land Rover Defender (Neuwertig)", "price": "90 \u20ac", "versand": null},
{"id": "1471862813", "set-id": "42114", "description": "Lego Technic Technik Anleitungen Teil2 42030 42043 42042 42114", "price": "15 \u20ac VB", "versand": "Versand m\u00f6glich"},
{"id": "1444795187", "set-id": "42029", "description": "Lego Technic Pick-up 42029", "price": "80 \u20ac", "versand": "Versand m\u00f6glich"},
{"id": "1444200056", "set-id": "42111", "description": "Lego Technic 42111 Fast & Furious Dodge", "price": "70 \u20ac", "versand": "Versand m\u00f6glich"},
{"id": "1096538449", "set-id": "42055", "description": "Lego Technic Technik 42009,42043,42030,42055,42082,8043", "price": " VB", "versand": "Versand m\u00f6glich"},
{"id": "763218889", "set-id": "42055", "description": "SUCHE: Lego 42055 2x mit Power Functions 8293", "price": " VB", "versand": "Gesuch"},
{"id": "1483278873", "set-id": "42055", "description": "Lego 42055 BWE Schaufelradbagger Anleitung OVP", "price": "5 \u20ac", "versand": "Versand m\u00f6glich"},
{"id": "1482869903", "set-id": "42115", "description": "Lego Technic Lamborghini Sian FKP 37 | 42115 | NEU & UNGE\u00d6FFNET", "price": "290 \u20ac", "versand": "Versand m\u00f6glich"},
{"id": "1479554251", "set-id": "42115", "description": "LEGO Technic 42115 Lamborghini Si\u00e1n FKP 37 NEU", "price": "299 \u20ac", "versand": "Versand m\u00f6glich"},
{"id": "1487537800", "set-id": "42115", "description": "Lego Technic Lamborghini Sian 42115 NEU", "price": "299 \u20ac VB", "versand": "Versand m\u00f6glich"},
{"id": "1483250326", "set-id": "42094", "description": "Lego Technic Raupenlader 42094", "price": "50 \u20ac", "versand": "Versand m\u00f6glich"},
{"id": "1480775584", "set-id": "42094", "description": "Lego Technic 42094 Laderaupe", "price": "50 \u20ac", "versand": null},
{"id": "1487178907", "set-id": "42078", "description": "Lego Technic 42078 Mack Anthem", "price": "100 \u20ac", "versand": "Versand m\u00f6glich"},
{"id": "1472626485", "set-id": "42110", "description": "Lego Technic 42110 Land Rover Defender", "price": "90 \u20ac VB", "versand": null},
{"id": "1488875028", "set-id": "42110", "description": "LEGO 42110 Technic Land Rover Defender", "price": "99 \u20ac", "versand": "Versand m\u00f6glich"},
{"id": "1485833284", "set-id": "42110", "description": "Lego Technic Defender 42110 inkl. Bauanleitung und OVP", "price": "100 \u20ac", "versand": "Versand m\u00f6glich"},
{"id": "1484800978", "set-id": "42114", "description": "Lego Technic, 42114;Volvo Dumper", "price": "185 \u20ac", "versand": "Versand m\u00f6glich"},
{"id": "1487948685", "set-id": "42114", "description": "LEGO\u00ae Technic 42114 VOLVO A60H Knickgelenk-Kipper mit App NEU", "price": "198 \u20ac", "versand": "Versand m\u00f6glich"},
{"id": "1302119259", "set-id": "42029", "description": "Lego Technik 42029 Pick-up Truck", "price": "80 \u20ac", "versand": "Versand m\u00f6glich"},
{"id": "1480614296", "set-id": "42029", "description": "LEGO 42029 Powertruck inkl. 8293 Powerpack", "price": "85 \u20ac", "versand": "Versand m\u00f6glich"},
{"id": "1428385269", "set-id": "42111", "description": "LEGO\u00ae Technic 42111 Technic Dom's Dodge Charger", "price": "70 \u20ac", "versand": "Versand m\u00f6glich"},
{"id": "1452921000", "set-id": "42111", "description": "Lego Technic 42111 Dom\u2018s Charger", "price": "70 \u20ac VB", "versand": "Versand m\u00f6glich"},
{"id": "1210407260", "set-id": "42055", "description": "Lego technic 42055 Schaufelradbagger Aufkleber sticker NEU", "price": "6 \u20ac", "versand": "Versand m\u00f6glich"},
{"id": "1487931597", "set-id": "42115", "description": "LEGO Technic 42115 - Lamborghini Si\u00e1n FKP 37", "price": "300 \u20ac", "versand": "Versand m\u00f6glich"},
{"id": "1467890466", "set-id": "42115", "description": "Lego Technik 42115 Lamborghini", "price": "300 \u20ac", "versand": "Versand m\u00f6glich"},
{"id": "1475440626", "set-id": "42094", "description": "Lego Technic Raupenlader 42094", "price": "50 \u20ac", "versand": "Versand m\u00f6glich"},
{"id": "1470565540", "set-id": "42094", "description": "Lego Technik Radlader/ laster 42094", "price": "50 \u20ac", "versand": null},
{"id": "1450086171", "set-id": "42110", "description": "LEGO Technic Land Rover Defender 42110", "price": "105 \u20ac VB", "versand": "Versand m\u00f6glich"},
{"id": "1442427836", "set-id": "42110", "description": "Lego Technik Land Rover Defender (42110)", "price": "105 \u20ac VB", "versand": null},
{"id": "1488781560", "set-id": "42114", "description": "Lego Technic 42114- 6x6 Volvo Articulated Hauler", "price": "199 \u20ac VB", "versand": "Versand m\u00f6glich"},
{"id": "1475112547", "set-id": "42029", "description": "LEGO Technic Pick-Up Truck 42029", "price": "85 \u20ac", "versand": "Versand m\u00f6glich"},
{"id": "1353357144", "set-id": "42111", "description": "Lego Technik 42111 Fast&Furious Auto", "price": "70 \u20ac VB", "versand": "Versand m\u00f6glich"},
{"id": "1184294491", "set-id": "42055", "description": "Lego technic 42055 Schaufelradbagger Bauanleitung NEU Anleitung", "price": "7 \u20ac", "versand": "Versand m\u00f6glich"},
{"id": "1483986657", "set-id": "42115", "description": "LEGO 42115 Technic Lamborghini Si\u00e1n FKP 37 NEU OVP", "price": "310 \u20ac", "versand": "Versand m\u00f6glich"},
{"id": "1488865642", "set-id": "42115", "description": "Lego Technic 42115 Lamborghini Si\u00e1n NEU & OVP", "price": "315 \u20ac", "versand": "Versand m\u00f6glich"},
{"id": "1464647511", "set-id": "42094", "description": "Lego Technic Raupenlader 42094", "price": "50 \u20ac", "versand": "Versand m\u00f6glich"},
{"id": "1453694961", "set-id": "42094", "description": "LEGO Technic - Raupenlader - 42094", "price": "50 \u20ac", "versand": null},
{"id": "1480933991", "set-id": "42094", "description": "LEGO Technic Set 42094", "price": "50 \u20ac VB", "versand": "Versand m\u00f6glich"},
{"id": "1471965604", "set-id": "42110", "description": "Lego Technic 42110 Land Rover Defender bei Abholung 100\u20ac", "price": "110 \u20ac", "versand": "Versand m\u00f6glich"},
{"id": "1448007188", "set-id": "42110", "description": "LEGO 42110 Technic Land Rover Defender NEU in OVP", "price": "110 \u20ac", "versand": null},
{"id": "1483660541", "set-id": "42114", "description": "Lego Technic Volvo Dumper 42114", "price": "200 \u20ac VB", "versand": "Versand m\u00f6glich"},
{"id": "1485652060", "set-id": "42029", "description": "Inkl. Versand - Lego Technic 42029 Roter Pickup Truck Technik", "price": "85 \u20ac VB", "versand": "Versand m\u00f6glich"},
{"id": "1414573700", "set-id": "42111", "description": "Lego Technic 42111 Doms Charger", "price": "73 \u20ac", "versand": "Versand m\u00f6glich"},
{"id": "1375197020", "set-id": "42055", "description": "Lego Technic Aufkleber 42055", "price": "10 \u20ac", "versand": "Versand m\u00f6glich"},
{"id": "1483873541", "set-id": "42115", "description": "LEGO Technic 42115 Lamborghini Si\u00e1n FKP 37 NEU", "price": "325 \u20ac", "versand": "Versand m\u00f6glich"},
{"id": "1478558722", "set-id": "42115", "description": "Lego Technic 42115 Lamborghini Sian Neu & OVP MISB", "price": "325 \u20ac", "versand": "Versand m\u00f6glich"},
{"id": "1479962681", "set-id": "42094", "description": "Lego Technik Lader 42094", "price": "50 \u20ac VB", "versand": "Versand m\u00f6glich"},
{"id": "1453839643", "set-id": "42110", "description": "LEGO\u00ae Technic Land Rover Defender 42110", "price": "110 \u20ac VB", "versand": "Versand m\u00f6glich"},
{"id": "1453713919", "set-id": "42110", "description": "Lego 42110  LrD", "price": "110 \u20ac VB", "versand": "Versand m\u00f6glich"},
{"id": "1480481442", "set-id": "42114", "description": "Lego Technik 42114 Neu/OVP mit Siegel", "price": "210 \u20ac VB", "versand": "Versand m\u00f6glich"},
{"id": "1476950870", "set-id": "42114", "description": "Lego technic 42114 neu ovp Preis inklusive Lieferung", "price": "220 \u20ac", "versand": "Versand m\u00f6glich"},
{"id": "1484075351", "set-id": "42114", "description": "LEGO\u00ae Technic 42114 Knickgelenkter Volvo-Dumper", "price": "245 \u20ac", "versand": null},
{"id": "1441452187", "set-id": "42111", "description": "LEGO 42111 Dodge Charger", "price": "73 \u20ac VB", "versand": "Versand m\u00f6glich"},
{"id": "1479879423", "set-id": "42111", "description": "LEGO Dom's Dodge Charger 42111 Technik Neu", "price": "75 \u20ac", "versand": null},
{"id": "1489297066", "set-id": "42111", "description": "Lego Dodge Technic 42111", "price": "75 \u20ac VB", "versand": "Versand m\u00f6glich"},
{"id": "1459622458", "set-id": "42055", "description": "Lego Technic 42055 MK III Steinbagger Bauanleitung", "price": "12 \u20ac", "versand": "Versand m\u00f6glich"},
{"id": "1484866314", "set-id": "42055", "description": "Bauanleitung Lego 42055", "price": "13 \u20ac VB", "versand": "Versand m\u00f6glich"},
{"id": "1476530556", "set-id": "42115", "description": "Lego 42115 \u201eNeu&Ovp\"", "price": "330 \u20ac", "versand": "Versand m\u00f6glich"},
{"id": "1471258454", "set-id": "42115", "description": "LEGO 42115 Lamborghini Si\u00e1n FKP 37", "price": "333 \u20ac", "versand": "Versand m\u00f6glich"},
{"id": "1478021171", "set-id": "42111", "description": "LEGO 42111 - Technic Dom's Dodge Charger Fast & Furious NEU", "price": "75 \u20ac VB", "versand": "Versand m\u00f6glich"},
{"id": "1472987611", "set-id": "42111", "description": "LEGO 42111 Technic|Fast and Furious: Dom's Dodge Charger|NeuOVP", "price": "78 \u20ac", "versand": "Versand m\u00f6glich"},
{"id": "1476757074", "set-id": "42115", "description": "LEGO 42115 - Lamborghini Si\u00e1n FKP 37 OVP", "price": "339 \u20ac VB", "versand": "Versand m\u00f6glich"},
{"id": "1484930519", "set-id": "42115", "description": "\u2714 Lego Technic Lamborghini Sian FKP 37 (42115) | BRANDNEU | OVP \u2714", "price": "345 \u20ac", "versand": "Versand m\u00f6glich"},
{"id": "1478215534", "set-id": "42115", "description": "\u2714 Lego Technic Lamborghini Sian FKP 37 (42115) | BRANDNEU | OVP \u2714", "price": "345 \u20ac", "versand": "Versand m\u00f6glich"},
{"id": "1477175217", "set-id": "42111", "description": "LEGO\u00ae Technic 42111 Dom's Dodge Charger, NEU & OVP", "price": "79 \u20ac", "versand": "Versand m\u00f6glich"},
{"id": "1480695492", "set-id": "42111", "description": "LEGO Technic 42111 Fast&Furious", "price": "80 \u20ac", "versand": "Versand m\u00f6glich"},
{"id": "1471361073", "set-id": "42111", "description": "LEGO Technic - Dom's Dodge Charger 42111 NEU OVP Fast & Furious", "price": "80 \u20ac", "versand": "Versand m\u00f6glich"},
{"id": "1473446411", "set-id": "42115", "description": "LEGO\u00ae Technic 42115 Lamborghini Si\u00e1n FKP 37 NEU Vorr\u00e4tig", "price": "349 \u20ac", "versand": "Versand m\u00f6glich"},
{"id": "1475841928", "set-id": "42115", "description": "LEGO Technic 42115 Lamborghini Si\u00e1n FKP 37", "price": "350 \u20ac", "versand": "Versand m\u00f6glich"},
{"id": "1483584062", "set-id": "42115", "description": "LEGO Technic 42115 inkl. Licht und Motoren", "price": "450 \u20ac", "versand": "Versand m\u00f6glich"}
]